aggregator/__init__.py
aggregator/claude_integration.py
aggregator/commonllm.py
aggregator/config.py
aggregator/gemini_integration.py
aggregator/mistral_integration.py
aggregator/openai_integration.py
pilot_py_hub_aggregator-0.0.1.dist-info/LICENSE
pilot_py_hub_aggregator-0.0.1.dist-info/METADATA
pilot_py_hub_aggregator-0.0.1.dist-info/WHEEL
pilot_py_hub_aggregator-0.0.1.dist-info/top_level.txt
pilot_py_hub_aggregator-0.0.1.dist-info/RECORD
