Metadata-Version: 2.1
Name: pilot-py-hub-aggregator
Version: 0.0.1
Summary: A package for generating code using various AI models.
Home-page: https://github.com/lishu-gupta-pilot-tech/pilot-py-hub
Author: Piyush Kumar
Author-email: piyush@pilot-tech.co
Classifier: Programming Language :: Python :: 3
Classifier: License :: OSI Approved :: MIT License
Classifier: Operating System :: OS Independent
Requires-Python: >=3.6
License-File: LICENSE
Requires-Dist: google-generativeai
